{"v":"5.12.2","fr":30,"ip":0,"op":60,"w":1080,"h":1080,"nm":"Thunder","ddd":0,"assets":[],"layers":[{"ddd":0,"ind":1,"ty":4,"nm":"thunder","sr":1,"ks":{"o":{"a":0,"k":100,"ix":11},"r":{"a":1,"k":[{"i":{"x":[0.664],"y":[1]},"o":{"x":[0.813],"y":[0]},"t":0,"s":[-50]},{"i":{"x":[0.438],"y":[1]},"o":{"x":[0.671],"y":[0]},"t":20,"s":[20]},{"t":50,"s":[-50]}],"ix":10},"p":{"a":1,"k":[{"i":{"x":0.833,"y":1},"o":{"x":0.167,"y":0},"t":5,"s":[565.159,540.33,0],"to":[0,4.167,0],"ti":[0,0,0]},{"i":{"x":0.833,"y":1},"o":{"x":0.167,"y":0},"t":25,"s":[565.159,565.33,0],"to":[0,0,0],"ti":[0,4.167,0]},{"t":55,"s":[565.159,540.33,0]}],"ix":2,"l":2},"a":{"a":0,"k":[474.915,336.685,0],"ix":1,"l":2},"s":{"a":1,"k":[{"i":{"x":[0.456,0.456,0.833],"y":[1,1,1]},"o":{"x":[0.688,0.688,0.333],"y":[0,0,0]},"t":5,"s":[100,100,100]},{"i":{"x":[0.587,0.587,0.833],"y":[1,1,1]},"o":{"x":[0.758,0.758,0.167],"y":[0,0,0]},"t":25,"s":[184,184,100]},{"t":55,"s":[100,100,100]}],"ix":6,"l":2}},"ao":0,"shapes":[{"ty":"gr","it":[{"ind":0,"ty":"sh","ix":1,"ks":{"a":1,"k":[{"i":{"x":0.667,"y":1},"o":{"x":0.333,"y":0},"t":0,"s":[{"i":[[0,0],[0,0],[0,0],[0,0],[0,0],[0,0]],"o":[[0,0],[0,0],[0,0],[0,0],[0,0],[0,0]],"v":[[-4.317,20.473],[-66.644,42.462],[10.51,-143.874],[-6.878,-14.53],[60.841,-35.712],[-21.328,141.322]],"c":true}]},{"t":14.5,"s":[{"i":[[0,0],[0,0],[0,0],[0,0],[0,0],[0,0]],"o":[[0,0],[0,0],[0,0],[0,0],[0,0],[0,0]],"v":[[-1.649,14.811],[-0.207,66.244],[-29.84,-126.9],[-6.678,-6.639],[-5.931,-39.922],[19.412,136.489]],"c":true}]}],"ix":2},"nm":"Path 1","mn":"ADBE Vector Shape - Group","hd":false},{"ty":"fl","c":{"a":0,"k":[0.450980392157,0.443137254902,0.96862745098,1],"ix":4},"o":{"a":0,"k":100,"ix":5},"r":1,"bm":0,"nm":"Fill 1","mn":"ADBE Vector Graphic - Fill","hd":false},{"ty":"tr","p":{"a":0,"k":[474.915,336.685],"ix":2},"a":{"a":0,"k":[0,0],"ix":1},"s":{"a":0,"k":[100,100],"ix":3},"r":{"a":0,"k":0,"ix":6},"o":{"a":0,"k":100,"ix":7},"sk":{"a":0,"k":0,"ix":4},"sa":{"a":0,"k":0,"ix":5},"nm":"Transform"}],"nm":"Group 1","np":2,"cix":2,"bm":0,"ix":1,"mn":"ADBE Vector Group","hd":false},{"ty":"gr","it":[{"ind":0,"ty":"sh","ix":1,"ks":{"a":1,"k":[{"i":{"x":0.833,"y":0.833},"o":{"x":0.333,"y":0},"t":0,"s":[{"i":[[0,0],[0,0],[0,0],[0,0]],"o":[[0,0],[0,0],[0,0],[0,0]],"v":[[-24.449,51.86],[-31.671,49.118],[45.334,-137.115],[52.705,-134.477]],"c":true}]},{"i":{"x":0.667,"y":1},"o":{"x":0.167,"y":0.167},"t":5,"s":[{"i":[[0,0],[0,0],[0,0],[0,0]],"o":[[0,0],[0,0],[0,0],[0,0]],"v":[[-6.419,58.316],[-22.3,59.575],[25.393,-128.467],[41.382,-129.841]],"c":true}]},{"t":14.5,"s":[{"i":[[0,0],[0,0],[0,0],[0,0]],"o":[[0,0],[0,0],[0,0],[0,0]],"v":[[41.754,75.284],[3.014,87.103],[-26.684,-105.713],[12.06,-117.68]],"c":true}]}],"ix":2},"nm":"Path 1","mn":"ADBE Vector Shape - Group","hd":false},{"ty":"fl","c":{"a":0,"k":[0.580392156863,0.576470588235,1,1],"ix":4},"o":{"a":0,"k":100,"ix":5},"r":1,"bm":0,"nm":"Fill 1","mn":"ADBE Vector Graphic - Fill","hd":false},{"ty":"tr","p":{"a":0,"k":[432.962,327.344],"ix":2},"a":{"a":0,"k":[0,0],"ix":1},"s":{"a":0,"k":[100,100],"ix":3},"r":{"a":0,"k":0,"ix":6},"o":{"a":0,"k":100,"ix":7},"sk":{"a":0,"k":0,"ix":4},"sa":{"a":0,"k":0,"ix":5},"nm":"Transform"}],"nm":"Group 6","np":2,"cix":2,"bm":0,"ix":2,"mn":"ADBE Vector Group","hd":false},{"ty":"gr","it":[{"ind":0,"ty":"sh","ix":1,"ks":{"a":1,"k":[{"i":{"x":0.833,"y":0.833},"o":{"x":0.333,"y":0},"t":0,"s":[{"i":[[0,0],[0,0],[0,0],[0,0]],"o":[[0,0],[0,0],[0,0],[0,0]],"v":[[-6.425,-0.713],[-15.1,-3.717],[52.618,-24.899],[61.293,-21.895]],"c":true}]},{"i":{"x":0.833,"y":0.833},"o":{"x":0.167,"y":0.167},"t":5,"s":[{"i":[[0,0],[0,0],[0,0],[0,0]],"o":[[0,0],[0,0],[0,0],[0,0]],"v":[[-5.973,7.195],[-19.101,2.151],[33.094,-22.43],[42.225,-23.563]],"c":true}]},{"i":{"x":0.667,"y":1},"o":{"x":0.167,"y":0.167},"t":8.5,"s":[{"i":[[0,0],[0,0],[0,0],[0,0]],"o":[[0,0],[0,0],[0,0],[0,0]],"v":[[-7.609,9.076],[-19.407,12.173],[9.821,-18.548],[19.525,-24.88]],"c":true}]},{"t":14.5,"s":[{"i":[[0,0],[0,0],[0,0],[0,0]],"o":[[0,0],[0,0],[0,0],[0,0]],"v":[[-2.111,29.712],[-12.446,41.766],[-15.786,-14.275],[-5.451,-26.328]],"c":true}]}],"ix":2},"nm":"Path 1","mn":"ADBE Vector Shape - Group","hd":false},{"ty":"fl","c":{"a":0,"k":[0.780392156863,0.780392156863,0.929411764706,1],"ix":4},"o":{"a":0,"k":100,"ix":5},"r":1,"bm":0,"nm":"Fill 1","mn":"ADBE Vector Graphic - Fill","hd":false},{"ty":"tr","p":{"a":0,"k":[474.418,323.166],"ix":2},"a":{"a":0,"k":[0,0],"ix":1},"s":{"a":0,"k":[100,100],"ix":3},"r":{"a":0,"k":0,"ix":6},"o":{"a":0,"k":100,"ix":7},"sk":{"a":0,"k":0,"ix":4},"sa":{"a":0,"k":0,"ix":5},"nm":"Transform"}],"nm":"Group 5","np":2,"cix":2,"bm":0,"ix":3,"mn":"ADBE Vector Group","hd":false},{"ty":"gr","it":[{"ind":0,"ty":"sh","ix":1,"ks":{"a":1,"k":[{"i":{"x":0.833,"y":0.833},"o":{"x":0.333,"y":0},"t":0,"s":[{"i":[[0,0],[0,0],[0,0],[0,0]],"o":[[0,0],[0,0],[0,0],[0,0]],"v":[[-68.731,55.726],[-74.245,51.802],[-57.085,-69.148],[-51.894,-65.293]],"c":true}]},{"i":{"x":0.667,"y":1},"o":{"x":0.167,"y":0.167},"t":5,"s":[{"i":[[0,0],[0,0],[0,0],[0,0]],"o":[[0,0],[0,0],[0,0],[0,0]],"v":[[-58.068,54.741],[-71.905,53.729],[-64.425,-68.444],[-50.85,-67.473]],"c":true}]},{"t":14.5,"s":[{"i":[[0,0],[0,0],[0,0],[0,0]],"o":[[0,0],[0,0],[0,0],[0,0]],"v":[[-28.464,51.365],[-64.271,58.04],[-82.35,-67.36],[-46.639,-74.003]],"c":true}]}],"ix":2},"nm":"Path 1","mn":"ADBE Vector Shape - Group","hd":false},{"ty":"fl","c":{"a":0,"k":[0.580392156863,0.576470588235,1,1],"ix":4},"o":{"a":0,"k":100,"ix":5},"r":1,"bm":0,"nm":"Fill 1","mn":"ADBE Vector Graphic - Fill","hd":false},{"ty":"tr","p":{"a":0,"k":[522.783,421.823],"ix":2},"a":{"a":0,"k":[0,0],"ix":1},"s":{"a":0,"k":[100,100],"ix":3},"r":{"a":0,"k":0,"ix":6},"o":{"a":0,"k":100,"ix":7},"sk":{"a":0,"k":0,"ix":4},"sa":{"a":0,"k":0,"ix":5},"nm":"Transform"}],"nm":"Group 4","np":2,"cix":2,"bm":0,"ix":4,"mn":"ADBE Vector Group","hd":false}],"ip":0,"op":14,"st":0,"ct":1,"bm":0},{"ddd":0,"ind":2,"ty":4,"nm":"thunder 2","parent":1,"sr":1,"ks":{"o":{"a":0,"k":100,"ix":11},"r":{"a":0,"k":0,"ix":10},"p":{"a":0,"k":[474.915,336.685,0],"ix":2,"l":2},"a":{"a":0,"k":[474.915,336.685,0],"ix":1,"l":2},"s":{"a":0,"k":[100,100,100],"ix":6,"l":2}},"ao":0,"shapes":[{"ty":"gr","it":[{"ind":0,"ty":"sh","ix":1,"ks":{"a":1,"k":[{"i":{"x":0.642,"y":1},"o":{"x":0.333,"y":0},"t":14,"s":[{"i":[[0,0],[0,0],[0,0],[0,0],[0,0],[0,0]],"o":[[0,0],[0,0],[0,0],[0,0],[0,0],[0,0]],"v":[[-46.627,21.007],[-31.638,70.707],[-61.804,-122.85],[-48.103,-0.986],[-59.615,-32.668],[-30.204,143.628]],"c":true}]},{"i":{"x":0.833,"y":1},"o":{"x":0.167,"y":0},"t":25,"s":[{"i":[[0,0],[0,0],[0,0],[0,0],[0,0],[0,0]],"o":[[0,0],[0,0],[0,0],[0,0],[0,0],[0,0]],"v":[[-25.169,26.018],[15.38,63.542],[87.375,-142.313],[0.255,-11.999],[-40.742,-60.61],[-95.521,150.337]],"c":true}]},{"i":{"x":0.833,"y":1},"o":{"x":0.167,"y":0},"t":35,"s":[{"i":[[0,0],[0,0],[0,0],[0,0],[0,0],[0,0]],"o":[[0,0],[0,0],[0,0],[0,0],[0,0],[0,0]],"v":[[-7.515,26.018],[-0.899,63.542],[10.847,-142.313],[-3.367,-11.999],[-10.056,-60.61],[-18.993,150.337]],"c":true}]},{"t":38,"s":[{"i":[[0,0],[0,0],[0,0],[0,0],[0,0],[0,0]],"o":[[0,0],[0,0],[0,0],[0,0],[0,0],[0,0]],"v":[[-25.847,29.491],[-27.815,66.977],[-9.118,-147.19],[-22.175,-8.354],[-19.335,-56.892],[-37.531,153.272]],"c":true}]}],"ix":2},"nm":"Path 1","mn":"ADBE Vector Shape - Group","hd":false},{"ty":"fl","c":{"a":0,"k":[0.450980392157,0.443137254902,0.96862745098,1],"ix":4},"o":{"a":0,"k":100,"ix":5},"r":1,"bm":0,"nm":"Fill 1","mn":"ADBE Vector Graphic - Fill","hd":false},{"ty":"tr","p":{"a":0,"k":[474.915,336.685],"ix":2},"a":{"a":0,"k":[0,0],"ix":1},"s":{"a":0,"k":[100,100],"ix":3},"r":{"a":0,"k":0,"ix":6},"o":{"a":0,"k":100,"ix":7},"sk":{"a":0,"k":0,"ix":4},"sa":{"a":0,"k":0,"ix":5},"nm":"Transform"}],"nm":"Group 1","np":2,"cix":2,"bm":0,"ix":1,"mn":"ADBE Vector Group","hd":false},{"ty":"gr","it":[{"ind":0,"ty":"sh","ix":1,"ks":{"a":1,"k":[{"i":{"x":0.642,"y":1},"o":{"x":0.333,"y":0},"t":14,"s":[{"i":[[0,0],[0,0],[0,0],[0,0]],"o":[[0,0],[0,0],[0,0],[0,0]],"v":[[10.207,79.761],[55.793,80.016],[25.802,-113.245],[-19.835,-113.641]],"c":true}]},{"i":{"x":0.833,"y":0.833},"o":{"x":0.167,"y":0},"t":25,"s":[{"i":[[0,0],[0,0],[0,0],[0,0]],"o":[[0,0],[0,0],[0,0],[0,0]],"v":[[57.192,72.915],[65.059,75.785],[137.275,-129.945],[129.346,-132.998]],"c":true}]},{"i":{"x":0.833,"y":0.833},"o":{"x":0.167,"y":0.167},"t":27.5,"s":[{"i":[[0,0],[0,0],[0,0],[0,0]],"o":[[0,0],[0,0],[0,0],[0,0]],"v":[[54.648,70.743],[53.832,72.895],[113.302,-132.497],[112.664,-132.301]],"c":true}]},{"i":{"x":0.833,"y":0.833},"o":{"x":0.167,"y":0.167},"t":28.5,"s":[{"i":[[0,0],[0,0],[0,0],[0,0]],"o":[[0,0],[0,0],[0,0],[0,0]],"v":[[8.348,59.082],[52.204,72.599],[104.74,-132.846],[74.697,-133.381]],"c":true}]},{"i":{"x":0.833,"y":0.833},"o":{"x":0.167,"y":0.167},"t":29,"s":[{"i":[[0,0],[0,0],[0,0],[0,0]],"o":[[0,0],[0,0],[0,0],[0,0]],"v":[[9.819,63.957],[51.39,72.451],[100.459,-133.02],[65.044,-133.728]],"c":true}]},{"i":{"x":0.833,"y":1},"o":{"x":0.167,"y":0.167},"t":32.5,"s":[{"i":[[0,0],[0,0],[0,0],[0,0]],"o":[[0,0],[0,0],[0,0],[0,0]],"v":[[1.136,68.425],[44.301,72.534],[69.512,-132.491],[26.285,-136.783]],"c":true}]},{"i":{"x":0.833,"y":1},"o":{"x":0.167,"y":0},"t":35,"s":[{"i":[[0,0],[0,0],[0,0],[0,0]],"o":[[0,0],[0,0],[0,0],[0,0]],"v":[[-8.884,64.577],[40.356,71.474],[53.138,-132.288],[3.837,-139.369]],"c":true}]},{"t":38,"s":[{"i":[[0,0],[0,0],[0,0],[0,0]],"o":[[0,0],[0,0],[0,0],[0,0]],"v":[[-36.207,67.313],[12.787,75.784],[32.565,-136.576],[-16.957,-136.12]],"c":true}]}],"ix":2},"nm":"Path 1","mn":"ADBE Vector Shape - Group","hd":false},{"ty":"fl","c":{"a":0,"k":[0.580392156863,0.576470588235,1,1],"ix":4},"o":{"a":0,"k":100,"ix":5},"r":1,"bm":0,"nm":"Fill 1","mn":"ADBE Vector Graphic - Fill","hd":false},{"ty":"tr","p":{"a":0,"k":[432.962,327.344],"ix":2},"a":{"a":0,"k":[0,0],"ix":1},"s":{"a":0,"k":[100,100],"ix":3},"r":{"a":0,"k":0,"ix":6},"o":{"a":0,"k":100,"ix":7},"sk":{"a":0,"k":0,"ix":4},"sa":{"a":0,"k":0,"ix":5},"nm":"Transform"}],"nm":"Group 6","np":2,"cix":2,"bm":0,"ix":2,"mn":"ADBE Vector Group","hd":false},{"ty":"gr","it":[{"ind":0,"ty":"sh","ix":1,"ks":{"a":1,"k":[{"i":{"x":0.642,"y":1},"o":{"x":0.333,"y":0},"t":14,"s":[{"i":[[0,0],[0,0],[0,0],[0,0]],"o":[[0,0],[0,0],[0,0],[0,0]],"v":[[-44.651,35.576],[-29.628,44.173],[-44.052,-10.485],[-59.075,-19.082]],"c":true}]},{"i":{"x":0.833,"y":0.833},"o":{"x":0.167,"y":0},"t":25,"s":[{"i":[[0,0],[0,0],[0,0],[0,0]],"o":[[0,0],[0,0],[0,0],[0,0]],"v":[[-0.384,6.227],[11.12,5.67],[-29.877,-42.94],[-40.227,-47.116]],"c":true}]},{"i":{"x":0.833,"y":0.833},"o":{"x":0.167,"y":0.167},"t":27.5,"s":[{"i":[[0,0],[0,0],[0,0],[0,0]],"o":[[0,0],[0,0],[0,0],[0,0]],"v":[[-0.311,4.365],[4.4,3.943],[-29.23,-44.517],[-33.879,-47.013]],"c":true}]},{"i":{"x":0.833,"y":1},"o":{"x":0.167,"y":0.167},"t":29,"s":[{"i":[[0,0],[0,0],[0,0],[0,0]],"o":[[0,0],[0,0],[0,0],[0,0]],"v":[[-2.947,8.166],[-3.214,7.845],[-27.622,-40.874],[-28.093,-42.14]],"c":true}]},{"i":{"x":0.833,"y":1},"o":{"x":0.167,"y":0},"t":35,"s":[{"i":[[0,0],[0,0],[0,0],[0,0]],"o":[[0,0],[0,0],[0,0],[0,0]],"v":[[-3.426,5.021],[-2.996,5.024],[-10.214,-46.915],[-10.58,-47.497]],"c":true}]},{"t":38,"s":[{"i":[[0,0],[0,0],[0,0],[0,0]],"o":[[0,0],[0,0],[0,0],[0,0]],"v":[[-22.261,8.304],[-21.831,8.321],[-21.421,-41.611],[-21.769,-42.203]],"c":true}]}],"ix":2},"nm":"Path 1","mn":"ADBE Vector Shape - Group","hd":false},{"ty":"fl","c":{"a":0,"k":[0.780392156863,0.780392156863,0.929411764706,1],"ix":4},"o":{"a":0,"k":100,"ix":5},"r":1,"bm":0,"nm":"Fill 1","mn":"ADBE Vector Graphic - Fill","hd":false},{"ty":"tr","p":{"a":0,"k":[474.418,323.166],"ix":2},"a":{"a":0,"k":[0,0],"ix":1},"s":{"a":0,"k":[100,100],"ix":3},"r":{"a":0,"k":0,"ix":6},"o":{"a":0,"k":100,"ix":7},"sk":{"a":0,"k":0,"ix":4},"sa":{"a":0,"k":0,"ix":5},"nm":"Transform"}],"nm":"Group 5","np":2,"cix":2,"bm":0,"ix":3,"mn":"ADBE Vector Group","hd":false},{"ty":"gr","it":[{"ind":0,"ty":"sh","ix":1,"ks":{"a":1,"k":[{"i":{"x":0.642,"y":1},"o":{"x":0.333,"y":0},"t":14,"s":[{"i":[[0,0],[0,0],[0,0],[0,0]],"o":[[0,0],[0,0],[0,0],[0,0]],"v":[[-78.059,58.502],[-37.291,54.665],[-58.128,-70.671],[-98.782,-66.831]],"c":true}]},{"i":{"x":0.833,"y":0.833},"o":{"x":0.167,"y":0},"t":25,"s":[{"i":[[0,0],[0,0],[0,0],[0,0]],"o":[[0,0],[0,0],[0,0],[0,0]],"v":[[-143.522,65.497],[-136.358,66.269],[-64.835,-58.053],[-75.073,-61.554]],"c":true}]},{"i":{"x":0.833,"y":0.833},"o":{"x":0.167,"y":0.167},"t":27.5,"s":[{"i":[[0,0],[0,0],[0,0],[0,0]],"o":[[0,0],[0,0],[0,0],[0,0]],"v":[[-127.202,65.886],[-127.342,65.337],[-81.312,-144.34],[-82.922,-144.021]],"c":true}]},{"i":{"x":0.833,"y":1},"o":{"x":0.167,"y":0.167},"t":29,"s":[{"i":[[0,0],[0,0],[0,0],[0,0]],"o":[[0,0],[0,0],[0,0],[0,0]],"v":[[-143.743,62.011],[-113.632,65.165],[-77.006,-145.953],[-105.042,-147.556]],"c":true}]},{"i":{"x":0.833,"y":1},"o":{"x":0.167,"y":0},"t":35,"s":[{"i":[[0,0],[0,0],[0,0],[0,0]],"o":[[0,0],[0,0],[0,0],[0,0]],"v":[[-119.866,58.056],[-66.807,63.592],[-57.546,-145.58],[-103.378,-145.284]],"c":true}]},{"t":38,"s":[{"i":[[0,0],[0,0],[0,0],[0,0]],"o":[[0,0],[0,0],[0,0],[0,0]],"v":[[-135.313,63.621],[-82.458,70.854],[-66.499,-137.913],[-115.328,-140.475]],"c":true}]}],"ix":2},"nm":"Path 1","mn":"ADBE Vector Shape - Group","hd":false},{"ty":"fl","c":{"a":0,"k":[0.580392156863,0.576470588235,1,1],"ix":4},"o":{"a":0,"k":100,"ix":5},"r":1,"bm":0,"nm":"Fill 1","mn":"ADBE Vector Graphic - Fill","hd":false},{"ty":"tr","p":{"a":0,"k":[522.783,421.823],"ix":2},"a":{"a":0,"k":[0,0],"ix":1},"s":{"a":0,"k":[100,100],"ix":3},"r":{"a":0,"k":0,"ix":6},"o":{"a":0,"k":100,"ix":7},"sk":{"a":0,"k":0,"ix":4},"sa":{"a":0,"k":0,"ix":5},"nm":"Transform"}],"nm":"Group 4","np":2,"cix":2,"bm":0,"ix":4,"mn":"ADBE Vector Group","hd":false}],"ip":14,"op":38,"st":1,"ct":1,"bm":0},{"ddd":0,"ind":3,"ty":4,"nm":"thunder 5","parent":1,"sr":1,"ks":{"o":{"a":0,"k":100,"ix":11},"r":{"a":0,"k":0,"ix":10},"p":{"a":0,"k":[474.915,336.685,0],"ix":2,"l":2},"a":{"a":0,"k":[474.915,336.685,0],"ix":1,"l":2},"s":{"a":0,"k":[100,100,100],"ix":6,"l":2}},"ao":0,"shapes":[{"ty":"gr","it":[{"ind":0,"ty":"sh","ix":1,"ks":{"a":1,"k":[{"i":{"x":0.667,"y":1},"o":{"x":0.333,"y":0},"t":38,"s":[{"i":[[0,0],[0,0],[0,0],[0,0],[0,0],[0,0]],"o":[[0,0],[0,0],[0,0],[0,0],[0,0],[0,0]],"v":[[-78.119,13.507],[-96.593,68.88],[-67.166,-145.965],[-77.717,-10.849],[-62.992,-46.202],[-92.711,149.539]],"c":true}]},{"t":47.5,"s":[{"i":[[0,0],[0,0],[0,0],[0,0],[0,0],[0,0]],"o":[[0,0],[0,0],[0,0],[0,0],[0,0],[0,0]],"v":[[-4.317,20.473],[-66.644,42.462],[10.51,-143.874],[-6.878,-14.53],[60.841,-35.712],[-21.328,141.322]],"c":true}]}],"ix":2},"nm":"Path 1","mn":"ADBE Vector Shape - Group","hd":false},{"ty":"fl","c":{"a":0,"k":[0.450980392157,0.443137254902,0.96862745098,1],"ix":4},"o":{"a":0,"k":100,"ix":5},"r":1,"bm":0,"nm":"Fill 1","mn":"ADBE Vector Graphic - Fill","hd":false},{"ty":"tr","p":{"a":0,"k":[474.915,336.685],"ix":2},"a":{"a":0,"k":[0,0],"ix":1},"s":{"a":0,"k":[100,100],"ix":3},"r":{"a":0,"k":0,"ix":6},"o":{"a":0,"k":100,"ix":7},"sk":{"a":0,"k":0,"ix":4},"sa":{"a":0,"k":0,"ix":5},"nm":"Transform"}],"nm":"Group 1","np":2,"cix":2,"bm":0,"ix":1,"mn":"ADBE Vector Group","hd":false},{"ty":"gr","it":[{"ind":0,"ty":"sh","ix":1,"ks":{"a":1,"k":[{"i":{"x":0.833,"y":0.833},"o":{"x":0.333,"y":0},"t":38,"s":[{"i":[[0,0],[0,0],[0,0],[0,0]],"o":[[0,0],[0,0],[0,0],[0,0]],"v":[[0.479,76.645],[-54.337,78.225],[-24.566,-140.217],[30.301,-141.955]],"c":true}]},{"i":{"x":0.833,"y":0.833},"o":{"x":0.167,"y":0.167},"t":40,"s":[{"i":[[0,0],[0,0],[0,0],[0,0]],"o":[[0,0],[0,0],[0,0],[0,0]],"v":[[-16.316,72.939],[-51.367,75.772],[-15.163,-138.284],[17.047,-140.494]],"c":true}]},{"i":{"x":0.833,"y":0.833},"o":{"x":0.167,"y":0.167},"t":41.5,"s":[{"i":[[0,0],[0,0],[0,0],[0,0]],"o":[[0,0],[0,0],[0,0],[0,0]],"v":[[-43.367,68.138],[-45.196,70.816],[-1.063,-134.879],[0.377,-135.936]],"c":true}]},{"i":{"x":0.667,"y":1},"o":{"x":0.167,"y":0.167},"t":43,"s":[{"i":[[0,0],[0,0],[0,0],[0,0]],"o":[[0,0],[0,0],[0,0],[0,0]],"v":[[-37.316,63.626],[-51.805,65.708],[3.446,-135.36],[18.039,-137.57]],"c":true}]},{"t":47.5,"s":[{"i":[[0,0],[0,0],[0,0],[0,0]],"o":[[0,0],[0,0],[0,0],[0,0]],"v":[[-24.449,51.86],[-31.671,49.118],[45.334,-137.115],[52.705,-134.477]],"c":true}]}],"ix":2},"nm":"Path 1","mn":"ADBE Vector Shape - Group","hd":false},{"ty":"fl","c":{"a":0,"k":[0.580392156863,0.576470588235,1,1],"ix":4},"o":{"a":0,"k":100,"ix":5},"r":1,"bm":0,"nm":"Fill 1","mn":"ADBE Vector Graphic - Fill","hd":false},{"ty":"tr","p":{"a":0,"k":[432.962,327.344],"ix":2},"a":{"a":0,"k":[0,0],"ix":1},"s":{"a":0,"k":[100,100],"ix":3},"r":{"a":0,"k":0,"ix":6},"o":{"a":0,"k":100,"ix":7},"sk":{"a":0,"k":0,"ix":4},"sa":{"a":0,"k":0,"ix":5},"nm":"Transform"}],"nm":"Group 6","np":2,"cix":2,"bm":0,"ix":2,"mn":"ADBE Vector Group","hd":false},{"ty":"gr","it":[{"ind":0,"ty":"sh","ix":1,"ks":{"a":1,"k":[{"i":{"x":0.833,"y":0.833},"o":{"x":0.333,"y":0},"t":38,"s":[{"i":[[0,0],[0,0],[0,0],[0,0]],"o":[[0,0],[0,0],[0,0],[0,0]],"v":[[-76.491,20.462],[-84.779,26.509],[-76.367,-25.251],[-62.448,-32.094]],"c":true}]},{"i":{"x":0.667,"y":1},"o":{"x":0.167,"y":0.167},"t":41.5,"s":[{"i":[[0,0],[0,0],[0,0],[0,0]],"o":[[0,0],[0,0],[0,0],[0,0]],"v":[[-54.967,13.957],[-66.106,4.672],[-38.656,-27.313],[-24.436,-28.961]],"c":true}]},{"t":47.5,"s":[{"i":[[0,0],[0,0],[0,0],[0,0]],"o":[[0,0],[0,0],[0,0],[0,0]],"v":[[-6.425,-0.713],[-15.1,-3.717],[52.618,-24.899],[61.293,-21.895]],"c":true}]}],"ix":2},"nm":"Path 1","mn":"ADBE Vector Shape - Group","hd":false},{"ty":"fl","c":{"a":0,"k":[0.780392156863,0.780392156863,0.929411764706,1],"ix":4},"o":{"a":0,"k":100,"ix":5},"r":1,"bm":0,"nm":"Fill 1","mn":"ADBE Vector Graphic - Fill","hd":false},{"ty":"tr","p":{"a":0,"k":[474.418,323.166],"ix":2},"a":{"a":0,"k":[0,0],"ix":1},"s":{"a":0,"k":[100,100],"ix":3},"r":{"a":0,"k":0,"ix":6},"o":{"a":0,"k":100,"ix":7},"sk":{"a":0,"k":0,"ix":4},"sa":{"a":0,"k":0,"ix":5},"nm":"Transform"}],"nm":"Group 5","np":2,"cix":2,"bm":0,"ix":3,"mn":"ADBE Vector Group","hd":false},{"ty":"gr","it":[{"ind":0,"ty":"sh","ix":1,"ks":{"a":1,"k":[{"i":{"x":0.833,"y":0.833},"o":{"x":0.333,"y":0},"t":38,"s":[{"i":[[0,0],[0,0],[0,0],[0,0]],"o":[[0,0],[0,0],[0,0],[0,0]],"v":[[-91.121,68.136],[-140.411,65.055],[-111.601,-132.22],[-62.449,-129.133]],"c":true}]},{"i":{"x":0.833,"y":0.833},"o":{"x":0.167,"y":0.167},"t":40,"s":[{"i":[[0,0],[0,0],[0,0],[0,0]],"o":[[0,0],[0,0],[0,0],[0,0]],"v":[[-108.665,64.624],[-132.651,62.674],[-96.994,-129.659],[-72.859,-128.765]],"c":true}]},{"i":{"x":0.833,"y":0.833},"o":{"x":0.167,"y":0.167},"t":41.5,"s":[{"i":[[0,0],[0,0],[0,0],[0,0]],"o":[[0,0],[0,0],[0,0],[0,0]],"v":[[-118.958,61.151],[-117.613,60.731],[-75.295,-125.784],[-73.702,-125.827]],"c":true}]},{"i":{"x":0.667,"y":1},"o":{"x":0.167,"y":0.167},"t":43,"s":[{"i":[[0,0],[0,0],[0,0],[0,0]],"o":[[0,0],[0,0],[0,0],[0,0]],"v":[[-101.917,58.422],[-112.614,59.237],[-99.09,-66.599],[-81.739,-75.158]],"c":true}]},{"t":47.5,"s":[{"i":[[0,0],[0,0],[0,0],[0,0]],"o":[[0,0],[0,0],[0,0],[0,0]],"v":[[-68.731,55.726],[-74.245,51.802],[-57.085,-69.148],[-51.894,-65.293]],"c":true}]}],"ix":2},"nm":"Path 1","mn":"ADBE Vector Shape - Group","hd":false},{"ty":"fl","c":{"a":0,"k":[0.580392156863,0.576470588235,1,1],"ix":4},"o":{"a":0,"k":100,"ix":5},"r":1,"bm":0,"nm":"Fill 1","mn":"ADBE Vector Graphic - Fill","hd":false},{"ty":"tr","p":{"a":0,"k":[522.783,421.823],"ix":2},"a":{"a":0,"k":[0,0],"ix":1},"s":{"a":0,"k":[100,100],"ix":3},"r":{"a":0,"k":0,"ix":6},"o":{"a":0,"k":100,"ix":7},"sk":{"a":0,"k":0,"ix":4},"sa":{"a":0,"k":0,"ix":5},"nm":"Transform"}],"nm":"Group 4","np":2,"cix":2,"bm":0,"ix":4,"mn":"ADBE Vector Group","hd":false}],"ip":38,"op":80,"st":30.5,"ct":1,"bm":0}],"markers":[],"props":{}}